LICENSE.rst
MANIFEST.in
README.rst
setup.py
src/bda/__init__.py
src/bda.disclaimer.egg-info/PKG-INFO
src/bda.disclaimer.egg-info/SOURCES.txt
src/bda.disclaimer.egg-info/dependency_links.txt
src/bda.disclaimer.egg-info/entry_points.txt
src/bda.disclaimer.egg-info/namespace_packages.txt
src/bda.disclaimer.egg-info/not-zip-safe
src/bda.disclaimer.egg-info/requires.txt
src/bda.disclaimer.egg-info/top_level.txt
src/bda/disclaimer/__init__.py
src/bda/disclaimer/configure.zcml
src/bda/disclaimer/disclaimer.py
src/bda/disclaimer/i18n.sh
src/bda/disclaimer/interfaces.py
src/bda/disclaimer/profiles.zcml
src/bda/disclaimer/browser/__init__.py
src/bda/disclaimer/browser/configure.zcml
src/bda/disclaimer/browser/disclaimer.pt
src/bda/disclaimer/browser/disclaimer.py
src/bda/disclaimer/locales/bda.disclaimer.pot
src/bda/disclaimer/locales/manual.pot
src/bda/disclaimer/locales/de/LC_MESSAGES/bda.disclaimer.mo
src/bda/disclaimer/locales/de/LC_MESSAGES/bda.disclaimer.po
src/bda/disclaimer/locales/en/LC_MESSAGES/bda.disclaimer.mo
src/bda/disclaimer/locales/en/LC_MESSAGES/bda.disclaimer.po
src/bda/disclaimer/profile/browserlayer.xml
src/bda/disclaimer/profile/metadata.xml