Metadata-Version: 1.1
Name: bda.disclaimer
Version: 1.1
Summary: Cookie based access restriction for Plone sites.
Home-page: http://pypi.python.org/pypi/bda.disclaimer
Author: BlueDynamics Alliance
Author-email: dev@bluedynamics.com
License: GPL
Keywords: plone cookie protection disclaimer
Platform: UNKNOWN
Classifier: Environment :: Web Environment
Classifier: Operating System :: OS Independent
Classifier: Programming Language :: Python
